[
    {
        "id" : 1,
        "title" : "Rolling in the Deep",
        "image" : "images/profile.jpg"
    },
    {
        "id" : 2,
        "title" : "Rolling in the Deep2",
        "image" : "images/singer01.jpg"
    },
    {
        "id" : 3,
        "title" : "Rolling in the Deep3",
        "image" : "images/singer03.jpg"
    },
    {
        "id" : 4,
        "title" : "Rolling in the Deep4",
        "image" : "images/singer02.jpg"
    },
    {
        "id" : 5,
        "title" : "Rolling in the Deep5",
        "image" : "images/singer02.jpg"
    },
    {
        "id" : 6,
        "title" : "Rolling in the Deep6",
        "image" : "images/singer01.jpg"
    },
    {
        "id" : 7,
        "title" : "Rolling in the Deep7",
        "image" : "images/profile.jpg"
    },
    {
        "id" : 8,
        "title" : "Rolling in the Deep8",
        "image" : "images/singer03.jpg"
    },
    {
        "id" : 9,
        "title" : "Rolling in the Deep9",
        "image" : "images/profile.jpg"
    },
    {
        "id" : 10,
        "title" : "Rolling in the Deep10",
        "image" : "images/singer03.jpg"
    },
    {
        "id" : 11,
        "title" : "Rolling in the Deep11",
        "image" : "images/singer02.jpg"
    },
    {
        "id" : 12,
        "title" : "Rolling in the Deep12",
        "image" : "images/singer01.jpg"
    }
]